{
    "Users": [
       {
         "Username": "admin",
         "Password": "Passwrd",
         "SavedSite": {
           "Siteusername": "Adminsusername",
           "Password": "Adminspassword",
           "Website Name": "Harveyswebsite"
         }
           
         }
       ,
       {
         "Username": "userone",
         "Password": "passwo1d",
         "SavedSite": {
            "Siteusername": "Myusername",
            "Password": "passkey13",
            "Website Name": "Harveyswebsite"
         }
        }
    ]
}